edautils/__init__.py
edautils/plot.py
edautils-0.1.4.dist-info/LICENSE
edautils-0.1.4.dist-info/METADATA
edautils-0.1.4.dist-info/WHEEL
edautils-0.1.4.dist-info/top_level.txt
edautils-0.1.4.dist-info/RECORD
